[{"line":1,"elements":[{"start_timestamp":"2026-04-27T03:16:16.914Z","before":[{"result":{"duration":12667263600,"status":"passed"},"match":{"location":"com.ixigo.testing.stepdefinition.Hook.setUp(io.cucumber.java.Scenario)"}}],"line":3,"name":"Search food using PNR","description":"","id":"food-delivery-in-train;search-food-using-pnr","after":[{"result":{"duration":10453116600,"status":"passed"},"match":{"location":"com.ixigo.testing.stepdefinition.Hook.tearDown(io.cucumber.java.Scenario)"}}],"type":"scenario","keyword":"Scenario","steps":[{"result":{"duration":1211310000,"status":"passed"},"line":4,"name":"User is on food delivery page","match":{"location":"com.ixigo.testing.stepdefinition.FoodSteps.open_food_page()"},"keyword":"Given "},{"result":{"duration":1859596100,"status":"passed"},"line":5,"name":"User enters PNR number \"1234567890\"","match":{"arguments":[{"val":"\"1234567890\"","offset":23}],"location":"com.ixigo.testing.stepdefinition.FoodSteps.enter_pnr(java.lang.String)"},"keyword":"When "},{"result":{"duration":12047580500,"status":"passed"},"line":6,"name":"User clicks search food","match":{"location":"com.ixigo.testing.stepdefinition.FoodSteps.click_search_food()"},"keyword":"And "},{"result":{"duration":10505276800,"status":"passed"},"line":7,"name":"User should see food results page","match":{"location":"com.ixigo.testing.stepdefinition.FoodSteps.verify_food_page()"},"keyword":"Then "}]}],"name":"Food Delivery in Train","description":"","id":"food-delivery-in-train","keyword":"Feature","uri":"file:src/test/java/com/ixigo/testing/featurefile/foodDelivery.feature","tags":[]},{"line":1,"elements":[{"start_timestamp":"2026-04-27T03:16:16.913Z","before":[{"result":{"duration":35580790100,"status":"passed"},"match":{"location":"com.ixigo.testing.stepdefinition.Hook.setUp(io.cucumber.java.Scenario)"}}],"line":3,"name":"Search train platform and proceed to booking","description":"","id":"platform-locator;search-train-platform-and-proceed-to-booking","after":[{"result":{"duration":615906500,"status":"passed"},"match":{"location":"com.ixigo.testing.stepdefinition.Hook.tearDown(io.cucumber.java.Scenario)"}}],"type":"scenario","keyword":"Scenario","steps":[{"result":{"duration":9286790400,"status":"passed"},"line":5,"name":"User is on platform locator page","match":{"location":"com.ixigo.testing.stepdefinition.PlatformSteps.user_on_platform_page()"},"keyword":"Given "},{"result":{"duration":3344392800,"status":"passed"},"line":6,"name":"User enters train number \"12605\"","match":{"arguments":[{"val":"\"12605\"","offset":25}],"location":"com.ixigo.testing.stepdefinition.PlatformSteps.user_enters_train(java.lang.String)"},"keyword":"When "},{"result":{"duration":350699000,"status":"passed"},"line":7,"name":"User clicks search platform","match":{"location":"com.ixigo.testing.stepdefinition.PlatformSteps.user_clicks_search_platform()"},"keyword":"And "},{"result":{"duration":37282128500,"status":"passed"},"line":8,"name":"User completes booking flow from platform","match":{"location":"com.ixigo.testing.stepdefinition.PlatformSteps.user_completes_booking_flow()"},"keyword":"And "},{"result":{"error_message":"java.lang.AssertionError: LOGIN POPUP not shown. URL: https://www.ixigo.com/search/result/train/MS/KKDI/30052026//1/0/0/0/all\r\n\tat org.testng.Assert.fail(Assert.java:110)\r\n\tat com.ixigo.testing.stepdefinition.CommonSteps.runFullPostBookFlow(CommonSteps.java:132)\r\n\tat com.ixigo.testing.stepdefinition.CommonSteps.verify_login_popup(CommonSteps.java:54)\r\n\tat ✽.User should see login popup(file:///C:/Users/Our_Power/IxigoFinalCopy/ixigo/src/test/java/com/ixigo/testing/featurefile/platform.feature:9)\r\n","duration":40468803100,"status":"failed"},"line":9,"name":"User should see login popup","match":{"location":"com.ixigo.testing.stepdefinition.CommonSteps.verify_login_popup()"},"keyword":"Then "}]}],"name":"Platform Locator","description":"","id":"platform-locator","keyword":"Feature","uri":"file:src/test/java/com/ixigo/testing/featurefile/platform.feature","tags":[]},{"line":1,"elements":[{"start_timestamp":"2026-04-27T03:16:16.915Z","before":[{"result":{"duration":37790317700,"status":"passed"},"match":{"location":"com.ixigo.testing.stepdefinition.Hook.setUp(io.cucumber.java.Scenario)"}}],"line":3,"name":"Book train using station module and verify login popup","description":"","id":"ixigo-station-booking-flow;book-train-using-station-module-and-verify-login-popup","after":[{"result":{"duration":290690900,"status":"passed"},"match":{"location":"com.ixigo.testing.stepdefinition.Hook.tearDown(io.cucumber.java.Scenario)"}}],"type":"scenario","keyword":"Scenario","steps":[{"result":{"duration":17154800,"status":"passed"},"line":5,"name":"User is on train page","match":{"location":"com.ixigo.testing.stepdefinition.StationSteps.user_on_train_page()"},"keyword":"Given "},{"result":{"duration":2362728700,"status":"passed"},"line":6,"name":"User navigates to station module","match":{"location":"com.ixigo.testing.stepdefinition.StationSteps.user_navigates_to_station_module()"},"keyword":"When "},{"result":{"duration":6408806600,"status":"passed"},"line":7,"name":"User enters station code \"AJJ\"","match":{"arguments":[{"val":"\"AJJ\"","offset":25}],"location":"com.ixigo.testing.stepdefinition.StationSteps.user_enters_station_code(java.lang.String)"},"keyword":"And "},{"result":{"duration":386165300,"status":"passed"},"line":8,"name":"User clicks search","match":{"location":"com.ixigo.testing.stepdefinition.StationSteps.user_clicks_search()"},"keyword":"And "},{"result":{"duration":4493839000,"status":"passed"},"line":9,"name":"User clicks book now","match":{"location":"com.ixigo.testing.stepdefinition.StationSteps.user_clicks_book_now()"},"keyword":"And "},{"result":{"duration":17871228900,"status":"passed"},"line":10,"name":"User selects AVL and books ticket","match":{"location":"com.ixigo.testing.stepdefinition.StationSteps.user_selects_avl_and_books()"},"keyword":"And "},{"result":{"duration":8400217300,"status":"passed"},"line":11,"name":"User should see login popup","match":{"location":"com.ixigo.testing.stepdefinition.CommonSteps.verify_login_popup()"},"keyword":"Then "}]}],"name":"Ixigo Station Booking Flow","description":"","id":"ixigo-station-booking-flow","keyword":"Feature","uri":"file:src/test/java/com/ixigo/testing/featurefile/station.feature","tags":[]},{"line":1,"elements":[{"start_timestamp":"2026-04-27T03:16:16.913Z","before":[{"result":{"duration":37179207500,"status":"passed"},"match":{"location":"com.ixigo.testing.stepdefinition.Hook.setUp(io.cucumber.java.Scenario)"}}],"line":19,"name":"Search train and proceed to booking","description":"","id":"train-search-by-name-or-number;search-train-and-proceed-to-booking;;2","after":[{"result":{"duration":444037300,"status":"passed"},"match":{"location":"com.ixigo.testing.stepdefinition.Hook.tearDown(io.cucumber.java.Scenario)"}}],"type":"scenario","keyword":"Scenario Outline","steps":[{"result":{"duration":5749735500,"status":"passed"},"line":8,"name":"User is on train name search page","match":{"location":"com.ixigo.testing.stepdefinition.TrainNameSteps.user_on_train_name_page()"},"keyword":"Given "},{"result":{"duration":3316443400,"status":"passed"},"line":9,"name":"User enters train name \"Pallavan Express\"","match":{"arguments":[{"val":"\"Pallavan Express\"","offset":23}],"location":"com.ixigo.testing.stepdefinition.TrainNameSteps.user_enters_train_name(java.lang.String)"},"keyword":"When "},{"result":{"duration":1933546500,"status":"passed"},"line":10,"name":"User selects train from list","match":{"location":"com.ixigo.testing.stepdefinition.TrainNameSteps.select_train()"},"keyword":"And "},{"result":{"duration":48290485700,"status":"passed"},"line":11,"name":"User selects available date","match":{"location":"com.ixigo.testing.stepdefinition.TrainNameSteps.select_date()"},"keyword":"And "},{"result":{"duration":3766744900,"status":"passed"},"line":12,"name":"User clicks on book","match":{"location":"com.ixigo.testing.stepdefinition.TrainNameSteps.user_clicks_book()"},"keyword":"And "},{"result":{"duration":8635466600,"status":"passed"},"line":13,"name":"User should see login popup","match":{"location":"com.ixigo.testing.stepdefinition.CommonSteps.verify_login_popup()"},"keyword":"Then "}]},{"start_timestamp":"2026-04-27T03:16:16.913Z","before":[{"result":{"duration":37793316900,"status":"passed"},"match":{"location":"com.ixigo.testing.stepdefinition.Hook.setUp(io.cucumber.java.Scenario)"}}],"line":20,"name":"Search train and proceed to booking","description":"","id":"train-search-by-name-or-number;search-train-and-proceed-to-booking;;3","after":[{"result":{"duration":570841000,"status":"passed"},"match":{"location":"com.ixigo.testing.stepdefinition.Hook.tearDown(io.cucumber.java.Scenario)"}}],"type":"scenario","keyword":"Scenario Outline","steps":[{"result":{"duration":4625365700,"status":"passed"},"line":8,"name":"User is on train name search page","match":{"location":"com.ixigo.testing.stepdefinition.TrainNameSteps.user_on_train_name_page()"},"keyword":"Given "},{"result":{"duration":3268981700,"status":"passed"},"line":9,"name":"User enters train name \"Chennai Express\"","match":{"arguments":[{"val":"\"Chennai Express\"","offset":23}],"location":"com.ixigo.testing.stepdefinition.TrainNameSteps.user_enters_train_name(java.lang.String)"},"keyword":"When "},{"result":{"duration":1482196900,"status":"passed"},"line":10,"name":"User selects train from list","match":{"location":"com.ixigo.testing.stepdefinition.TrainNameSteps.select_train()"},"keyword":"And "},{"result":{"duration":34640441300,"status":"passed"},"line":11,"name":"User selects available date","match":{"location":"com.ixigo.testing.stepdefinition.TrainNameSteps.select_date()"},"keyword":"And "},{"result":{"duration":5913797700,"status":"passed"},"line":12,"name":"User clicks on book","match":{"location":"com.ixigo.testing.stepdefinition.TrainNameSteps.user_clicks_book()"},"keyword":"And "},{"result":{"error_message":"java.lang.AssertionError: LOGIN POPUP not shown. URL: https://www.ixigo.com/trains/12610/seat-availability\r\n\tat org.testng.Assert.fail(Assert.java:110)\r\n\tat com.ixigo.testing.stepdefinition.CommonSteps.runFullPostBookFlow(CommonSteps.java:132)\r\n\tat com.ixigo.testing.stepdefinition.CommonSteps.verify_login_popup(CommonSteps.java:54)\r\n\tat ✽.User should see login popup(file:///C:/Users/Our_Power/IxigoFinalCopy/ixigo/src/test/java/com/ixigo/testing/featurefile/trainName.feature:13)\r\n","duration":40681460300,"status":"failed"},"line":13,"name":"User should see login popup","match":{"location":"com.ixigo.testing.stepdefinition.CommonSteps.verify_login_popup()"},"keyword":"Then "}]}],"name":"Train Search by Name or Number","description":"","id":"train-search-by-name-or-number","keyword":"Feature","uri":"file:src/test/java/com/ixigo/testing/featurefile/trainName.feature","tags":[]},{"line":1,"elements":[{"start_timestamp":"2026-04-27T03:16:16.915Z","before":[{"result":{"duration":34470017100,"status":"passed"},"match":{"location":"com.ixigo.testing.stepdefinition.Hook.setUp(io.cucumber.java.Scenario)"}}],"line":3,"name":"Validate booking flow till login popup","description":"","id":"vande-bharat-train-booking;validate-booking-flow-till-login-popup","after":[{"result":{"duration":278374800,"status":"passed"},"match":{"location":"com.ixigo.testing.stepdefinition.Hook.tearDown(io.cucumber.java.Scenario)"}}],"type":"scenario","keyword":"Scenario","steps":[{"result":{"duration":9014348000,"status":"passed"},"line":4,"name":"User is on Vande Bharat page","match":{"location":"com.ixigo.testing.stepdefinition.VandeBharatSteps.open_vande_page()"},"keyword":"Given "},{"result":{"duration":2813016300,"status":"passed"},"line":5,"name":"User enters from station \"ADI\"","match":{"arguments":[{"val":"\"ADI\"","offset":25}],"location":"com.ixigo.testing.stepdefinition.VandeBharatSteps.enter_from(java.lang.String)"},"keyword":"When "},{"result":{"duration":3459484200,"status":"passed"},"line":6,"name":"User enters to station \"MMCT\"","match":{"arguments":[{"val":"\"MMCT\"","offset":23}],"location":"com.ixigo.testing.stepdefinition.VandeBharatSteps.enter_to(java.lang.String)"},"keyword":"And "},{"result":{"duration":4869801800,"status":"passed"},"line":7,"name":"User selects journey date","match":{"location":"com.ixigo.testing.stepdefinition.VandeBharatSteps.select_date()"},"keyword":"And "},{"result":{"duration":3380457300,"status":"passed"},"line":8,"name":"User clicks search trains","match":{"location":"com.ixigo.testing.stepdefinition.VandeBharatSteps.click_search()"},"keyword":"And "},{"result":{"duration":62169739400,"status":"passed"},"line":9,"name":"User selects AVL train and books","match":{"location":"com.ixigo.testing.stepdefinition.VandeBharatSteps.select_and_book()"},"keyword":"And "},{"result":{"duration":9065898100,"status":"passed"},"line":10,"name":"Login popup should be displayed","match":{"location":"com.ixigo.testing.stepdefinition.CommonSteps.login_popup_should_be_displayed()"},"keyword":"Then "}]}],"name":"Vande Bharat Train Booking","description":"","id":"vande-bharat-train-booking","keyword":"Feature","uri":"file:src/test/java/com/ixigo/testing/featurefile/vandeBharat.feature","tags":[]}]